llm_devin.py
llm_devin-0.0.4.dist-info/licenses/LICENSE
llm_devin-0.0.4.dist-info/METADATA
llm_devin-0.0.4.dist-info/WHEEL
llm_devin-0.0.4.dist-info/entry_points.txt
llm_devin-0.0.4.dist-info/top_level.txt
llm_devin-0.0.4.dist-info/RECORD
