Metadata-Version: 2.4
Name: llm-devin
Version: 0.0.4
Summary: LLM plugin to access Devin API
Author-email: nikkie <takuyafjp+develop@gmail.com>
License-Expression: Apache-2.0
Project-URL: Homepage, https://github.com/ftnext/llm-devin
Project-URL: Changelog, https://github.com/ftnext/llm-devin/releases
Project-URL: Issues, https://github.com/ftnext/llm-devin/issues
Project-URL: CI, https://github.com/ftnext/llm-devin/actions
Keywords: llm,devin
Classifier: Development Status :: 1 - Planning
Classifier: Intended Audience :: Developers
Classifier: Intended Audience :: End Users/Desktop
Classifier: Intended Audience :: Science/Research
Classifier: Programming Language :: Python :: 3
Classifier: Programming Language :: Python :: 3.10
Classifier: Programming Language :: Python :: 3.11
Classifier: Programming Language :: Python :: 3.12
Classifier: Programming Language :: Python :: 3.13
Classifier: Topic :: Scientific/Engineering :: Artificial Intelligence
Classifier: Topic :: Text Processing :: Linguistic
Classifier: Topic :: Utilities
Requires-Python: >=3.10
License-File: LICENSE
Requires-Dist: llm
Requires-Dist: httpx
Requires-Dist: happy-python-logging
Requires-Dist: mcp
Provides-Extra: test
Requires-Dist: pytest; extra == "test"
Requires-Dist: respx; extra == "test"
Dynamic: license-file
